habitpy/__init__.py
habitpy/export.py
habitpy/graphs_data.py
habitpy/habitpy.py
habitpy/manage_habits.py
habitpy/reset.py
habitpy/setup.py
habitpy/track.py
habitpy/config/__init__.py
habitpy/config/config.py
habitpy/utils/__init__.py
habitpy/utils/cheers.py
habitpy/utils/date_adapter.py
habitpy/utils/functions.py
habitpy-0.1.11.dist-info/METADATA
habitpy-0.1.11.dist-info/WHEEL
habitpy-0.1.11.dist-info/entry_points.txt
habitpy-0.1.11.dist-info/top_level.txt
habitpy-0.1.11.dist-info/RECORD
