Metadata-Version: 2.4
Name: habitpy
Version: 0.1.11
Summary: Track your habits from the terminal
Author-email: Sebastián Figueroa <sebaj348@gmail.com>
License-Expression: MIT
Requires-Python: >=3.11
Requires-Dist: pandas
Requires-Dist: plotly
